README.md
setup.py
var_sd_card_writer.egg-info/PKG-INFO
var_sd_card_writer.egg-info/SOURCES.txt
var_sd_card_writer.egg-info/dependency_links.txt
var_sd_card_writer.egg-info/entry_points.txt
var_sd_card_writer.egg-info/top_level.txt
writer/__init__.py
writer/_information.py
writer/config.py
writer/device.py
writer/flasher.py
writer/ftp.py
writer/menubar.py
writer/select.py
writer/utils.py
writer/varwriter.py
writer/welcome.py
writer/writer.py