Metadata-Version: 2.1
Name: var-sd-card-writer
Version: 0.0.3
Summary: Variscite SD Card Writer Tool
Home-page: https://github.com/varigit/var-sd-card-writer
Author: Alifer Moraes, Diego Dorta
License: BSD-3-Clause
Platform: UNKNOWN
Classifier: Development Status :: 3 - Alpha
Classifier: Intended Audience :: Information Technology
Classifier: Natural Language :: English
Classifier: Operating System :: Other OS
Classifier: Programming Language :: Python :: 3.7
